LICENSE
MANIFEST.in
README.rst
requirements.txt
setup.py
htdocs/index.html
htdocs/runserver.py
htdocs/css/awesome-font.css
htdocs/css/awesome.css
htdocs/css/logo_anim.css
htdocs/css/main.css
htdocs/css/sm_main.css
htdocs/img/awesome-font.png
htdocs/img/bg.png
htdocs/img/codefade.png
htdocs/img/sprites.png
htdocs/img/transparency_pattern.png
htdocs/img/awesome-font/a.png
htdocs/img/awesome-font/b.png
htdocs/img/awesome-font/c.png
htdocs/img/awesome-font/d.png
htdocs/img/awesome-font/e.png
htdocs/img/awesome-font/f.png
htdocs/img/awesome-font/g.png
htdocs/img/awesome-font/h.png
htdocs/img/awesome-font/i.png
htdocs/img/awesome-font/j.png
htdocs/img/awesome-font/k.png
htdocs/img/awesome-font/l.png
htdocs/img/awesome-font/m.png
htdocs/img/awesome-font/n.png
htdocs/img/awesome-font/o.png
htdocs/img/awesome-font/p.png
htdocs/img/awesome-font/q.png
htdocs/img/awesome-font/r.png
htdocs/img/awesome-font/s.png
htdocs/img/awesome-font/t.png
htdocs/img/awesome-font/u.png
htdocs/img/awesome-font/v.png
htdocs/img/awesome-font/w.png
htdocs/img/awesome-font/x.png
htdocs/img/awesome-font/y.png
htdocs/img/awesome-font/z.png
htdocs/img/example-sprite/image1.png
htdocs/img/example-sprite/image2.png
htdocs/img/example-sprite/image3.png
htdocs/img/example-sprite/image4.png
htdocs/img/sprites/fork_me_on_github.png
htdocs/img/sprites/logo_01.png
htdocs/img/sprites/logo_02.png
htdocs/img/sprites/logo_03.png
htdocs/img/sprites/logo_04.png
htdocs/img/sprites/logo_05.png
htdocs/img/sprites/spritemapper.png
htdocs/img/sprites/yostudios.png
htdocs/js/highlight.pack.js
htdocs/js/main.js
htdocs/js/mootools-core.js
htdocs/js/mootools-more.js
htdocs/js/utils.js
spritecss/__init__.py
spritecss/config.py
spritecss/finder.py
spritecss/image.py
spritecss/main.py
spritecss/mapper.py
spritecss/png.py
spritecss/replacer.py
spritecss/stitch.py
spritecss/css/__init__.py
spritecss/css/parser.py
spritecss/packing/__init__.py
spritecss/packing/anneal.py
spritecss/packing/sprites.py
spritemapper.egg-info/PKG-INFO
spritemapper.egg-info/SOURCES.txt
spritemapper.egg-info/dependency_links.txt
spritemapper.egg-info/entry_points.txt
spritemapper.egg-info/top_level.txt
tests/__init__.py
