Metadata-Version: 1.0
Name: spritemapper
Version: 1.0.0
Summary: A suite for merging multiple images and generate corresponding CSS in one go
Home-page: http://yostudios.github.com/Spritemapper/
Author: Yo Studios AB
Author-email: opensource@yostudios.se
License: MIT/X11
Platform: UNKNOWN
